pinner/__init__.py
pinner/api.py
pinner/cli.py
pinner/exceptions.py
pinner-1.0.dist-info/DESCRIPTION.rst
pinner-1.0.dist-info/entry_points.txt
pinner-1.0.dist-info/METADATA
pinner-1.0.dist-info/metadata.json
pinner-1.0.dist-info/RECORD
pinner-1.0.dist-info/top_level.txt
pinner-1.0.dist-info/WHEEL
