Metadata-Version: 2.0
Name: pinner
Version: 1.0
Summary: A tiny console script to verify you have pinned all of your python requirements
Home-page: https://github.com/coagulant/pinner
Author: Ilya Baryshev
Author-email: baryshev@gmail.com
License: BSD
Keywords: pinner
Platform: UNKNOWN
Classifier: Development Status :: 4 - Beta
Classifier: Intended Audience :: Developers
Classifier: License :: OSI Approved :: BSD License
Classifier: Natural Language :: English
Classifier: Programming Language :: Python :: 2
Classifier: Programming Language :: Python :: 2.6
Classifier: Programming Language :: Python :: 2.7
Classifier: Programming Language :: Python :: 3
Classifier: Programming Language :: Python :: 3.3
Classifier: Programming Language :: Python :: 3.4
Requires-Dist: requirements-parser (>=0.0.6)
